neurondm/__init__.py
neurondm/auth-config.py
neurondm/build.py
neurondm/core.py
neurondm/example.py
neurondm/indicators.py
neurondm/lang.py
neurondm/orders.py
neurondm/phenotype_namespaces.py
neurondm/sheets.py
neurondm/simple.py
neurondm/models/__init__.py
neurondm/models/allen_cell_types.py
neurondm/models/allen_type_specimen_mapping.py
neurondm/models/apinat_npo.py
neurondm/models/apinat_pops_more.py
neurondm/models/basic_neurons.py
neurondm/models/bolew.py
neurondm/models/composer.py
neurondm/models/cuts.py
neurondm/models/huang2017.py
neurondm/models/keast2020.py
neurondm/models/ma2015.py
neurondm/models/nerves.py
neurondm/models/nlp.py
neurondm/models/pcl.py
neurondm/models/phenotype_direct.py
neurondm-0.1.9.data/data/share/neurondm/part-of-self.ttl
neurondm-0.1.9.data/data/share/neurondm/phenotype-core.ttl
neurondm-0.1.9.data/data/share/neurondm/phenotype-indicators.ttl
neurondm-0.1.9.data/data/share/neurondm/phenotypes.ttl
neurondm-0.1.9.dist-info/licenses/LICENSE
neurondm-0.1.9.dist-info/METADATA
neurondm-0.1.9.dist-info/WHEEL
neurondm-0.1.9.dist-info/top_level.txt
neurondm-0.1.9.dist-info/RECORD
