Metadata-Version: 2.4
Name: neurondm
Version: 0.1.9
Summary: A data model for neuron types.
Home-page: https://github.com/tgbugs/pyontutils/tree/master/neurondm
Author: Tom Gillespie
Author-email: tgbugs@gmail.com
License: MIT
Keywords: neuron types NIF ontology neuroscience phenotype OWL rdf rdflib data model
Classifier: Development Status :: 4 - Beta
Classifier: Programming Language :: Python :: 3.7
Classifier: Programming Language :: Python :: 3.8
Classifier: Programming Language :: Python :: 3.9
Classifier: Programming Language :: Python :: 3.10
Classifier: Programming Language :: Python :: 3.11
Classifier: Programming Language :: Python :: 3.12
Classifier: Programming Language :: Python :: 3.13
Classifier: Programming Language :: Python :: Implementation :: CPython
Classifier: Programming Language :: Python :: Implementation :: PyPy
Classifier: Operating System :: POSIX :: Linux
Classifier: Operating System :: MacOS :: MacOS X
Classifier: Operating System :: Microsoft :: Windows
Requires-Python: >=3.7
License-File: LICENSE
Requires-Dist: hyputils>=0.0.10
Requires-Dist: pyontutils>=0.1.38
Provides-Extra: dev
Requires-Dist: pytest-cov; extra == "dev"
Requires-Dist: wheel; extra == "dev"
Provides-Extra: test
Requires-Dist: pytest; extra == "test"
Requires-Dist: nifstd-tools>=0.0.6; extra == "test"
Provides-Extra: models
Requires-Dist: nifstd-tools>=0.0.6; extra == "models"
Provides-Extra: tasic
Requires-Dist: pandas; extra == "tasic"
Requires-Dist: anytree; extra == "tasic"
Provides-Extra: notebook
Requires-Dist: jupyter; extra == "notebook"
Dynamic: author
Dynamic: author-email
Dynamic: classifier
Dynamic: description
Dynamic: description-content-type
Dynamic: home-page
Dynamic: keywords
Dynamic: license
Dynamic: license-file
Dynamic: provides-extra
Dynamic: requires-dist
Dynamic: requires-python
Dynamic: summary
